<annotation>
	<folder>jpg</folder>
	<filename>125_60.jpeg</filename>
	<path>D:\&#34411;&#23475;\jpg\125.jpeg</path>
	<source>
		<database>Unknown</database>
	</source>
	<size>
		<width>256</width>
		<height>256</height>
		<depth>3</depth>
	</size>
	<segmented>0</segmented>
	<object>
		<name>liriomyza</name>
		<pose>Unspecified</pose>
		<truncated>0</truncated>
		<difficult>0</difficult>
		<bndbox updated="yes">
			<xmin>71</xmin>
			<ymin>128</ymin>
			<xmax>104</xmax>
			<ymax>149</ymax>
		</bndbox>
	</object>
	<object>
		<name>liriomyza</name>
		<pose>Unspecified</pose>
		<truncated>0</truncated>
		<difficult>0</difficult>
		<bndbox updated="yes">
			<xmin>206</xmin>
			<ymin>169</ymin>
			<xmax>247</xmax>
			<ymax>193</ymax>
		</bndbox>
	</object>
	<object>
		<name>liriomyza</name>
		<pose>Unspecified</pose>
		<truncated>0</truncated>
		<difficult>0</difficult>
		<bndbox updated="yes">
			<xmin>108</xmin>
			<ymin>39</ymin>
			<xmax>150</xmax>
			<ymax>63</ymax>
		</bndbox>
	</object>
	<object>
		<name>liriomyza</name>
		<pose>Unspecified</pose>
		<truncated>0</truncated>
		<difficult>0</difficult>
		<bndbox updated="yes">
			<xmin>177</xmin>
			<ymin>58</ymin>
			<xmax>194</xmax>
			<ymax>78</ymax>
		</bndbox>
	</object>
</annotation>