<annotation>
	<folder>jpg</folder>
	<filename>2587.jpg</filename>
	<path>D:\虫害\jpg\2587.jpg</path>
	<source>
		<database>Unknown</database>
	</source>
	<size>
		<width>256</width>
		<height>397</height>
		<depth>3</depth>
	</size>
	<segmented>0</segmented>
	<object>
		<name>red_spider</name>
		<pose>Unspecified</pose>
		<truncated>0</truncated>
		<difficult>0</difficult>
		<bndbox>
			<xmin>73</xmin>
			<ymin>52</ymin>
			<xmax>188</xmax>
			<ymax>326</ymax>
		</bndbox>
	</object>
</annotation>
