<annotation>
	<folder>jpg</folder>
	<filename>34_60.jpeg</filename>
	<path>D:\&#34411;&#23475;\jpg\34.jpeg</path>
	<source>
		<database>Unknown</database>
	</source>
	<size>
		<width>256</width>
		<height>256</height>
		<depth>3</depth>
	</size>
	<segmented>0</segmented>
	<object>
		<name>liriomyza</name>
		<pose>Unspecified</pose>
		<truncated>0</truncated>
		<difficult>0</difficult>
		<bndbox updated="yes">
			<xmin>106</xmin>
			<ymin>25</ymin>
			<xmax>179</xmax>
			<ymax>98</ymax>
		</bndbox>
	</object>
	<object>
		<name>liriomyza</name>
		<pose>Unspecified</pose>
		<truncated>0</truncated>
		<difficult>0</difficult>
		<bndbox updated="yes">
			<xmin>197</xmin>
			<ymin>126</ymin>
			<xmax>240</xmax>
			<ymax>172</ymax>
		</bndbox>
	</object>
	<object>
		<name>liriomyza</name>
		<pose>Unspecified</pose>
		<truncated>0</truncated>
		<difficult>0</difficult>
		<bndbox updated="yes">
			<xmin>138</xmin>
			<ymin>271</ymin>
			<xmax>179</xmax>
			<ymax>303</ymax>
		</bndbox>
	</object>
	<object>
		<name>liriomyza</name>
		<pose>Unspecified</pose>
		<truncated>0</truncated>
		<difficult>0</difficult>
		<bndbox updated="yes">
			<xmin>142</xmin>
			<ymin>238</ymin>
			<xmax>201</xmax>
			<ymax>272</ymax>
		</bndbox>
	</object>
	<object>
		<name>liriomyza</name>
		<pose>Unspecified</pose>
		<truncated>0</truncated>
		<difficult>0</difficult>
		<bndbox updated="yes">
			<xmin>148</xmin>
			<ymin>188</ymin>
			<xmax>229</xmax>
			<ymax>236</ymax>
		</bndbox>
	</object>
	<object>
		<name>liriomyza</name>
		<pose>Unspecified</pose>
		<truncated>0</truncated>
		<difficult>0</difficult>
		<bndbox updated="yes">
			<xmin>223</xmin>
			<ymin>265</ymin>
			<xmax>238</xmax>
			<ymax>289</ymax>
		</bndbox>
	</object>
	<object>
		<name>liriomyza</name>
		<pose>Unspecified</pose>
		<truncated>1</truncated>
		<difficult>0</difficult>
		<bndbox updated="yes">
			<xmin>230</xmin>
			<ymin>80</ymin>
			<xmax>295</xmax>
			<ymax>118</ymax>
		</bndbox>
	</object>
	<object>
		<name>liriomyza</name>
		<pose>Unspecified</pose>
		<truncated>0</truncated>
		<difficult>0</difficult>
		<bndbox updated="yes">
			<xmin>73</xmin>
			<ymin>208</ymin>
			<xmax>119</xmax>
			<ymax>250</ymax>
		</bndbox>
	</object>
	<object>
		<name>liriomyza</name>
		<pose>Unspecified</pose>
		<truncated>0</truncated>
		<difficult>0</difficult>
		<bndbox updated="yes">
			<xmin>71</xmin>
			<ymin>156</ymin>
			<xmax>144</xmax>
			<ymax>198</ymax>
		</bndbox>
	</object>
</annotation>