<annotation>
	<folder>jpg</folder>
	<filename>944.jpg</filename>
	<path>D:\虫害\jpg\944.jpg</path>
	<source>
		<database>Unknown</database>
	</source>
	<size>
		<width>299</width>
		<height>299</height>
		<depth>3</depth>
	</size>
	<segmented>0</segmented>
	<object>
		<name>Tobacco_budworm</name>
		<pose>Unspecified</pose>
		<truncated>0</truncated>
		<difficult>0</difficult>
		<bndbox>
			<xmin>111</xmin>
			<ymin>87</ymin>
			<xmax>232</xmax>
			<ymax>161</ymax>
		</bndbox>
	</object>
</annotation>
