<annotation>
	<folder>jpg</folder>
	<filename>2448.JPG</filename>
	<path>D:\虫害\jpg\2448.JPG</path>
	<source>
		<database>Unknown</database>
	</source>
	<size>
		<width>256</width>
		<height>503</height>
		<depth>3</depth>
	</size>
	<segmented>0</segmented>
	<object>
		<name>red_spider</name>
		<pose>Unspecified</pose>
		<truncated>0</truncated>
		<difficult>0</difficult>
		<bndbox>
			<xmin>30</xmin>
			<ymin>28</ymin>
			<xmax>201</xmax>
			<ymax>446</ymax>
		</bndbox>
	</object>
</annotation>
