<annotation>
	<folder>jpg</folder>
	<filename>767.jpg</filename>
	<path>D:\虫害\jpg\767.jpg</path>
	<source>
		<database>Unknown</database>
	</source>
	<size>
		<width>800</width>
		<height>800</height>
		<depth>3</depth>
	</size>
	<segmented>0</segmented>
	<object>
		<name>thrips</name>
		<pose>Unspecified</pose>
		<truncated>0</truncated>
		<difficult>0</difficult>
		<bndbox>
			<xmin>454</xmin>
			<ymin>490</ymin>
			<xmax>503</xmax>
			<ymax>532</ymax>
		</bndbox>
	</object>
	<object>
		<name>thrips</name>
		<pose>Unspecified</pose>
		<truncated>0</truncated>
		<difficult>0</difficult>
		<bndbox>
			<xmin>350</xmin>
			<ymin>303</ymin>
			<xmax>376</xmax>
			<ymax>376</ymax>
		</bndbox>
	</object>
	<object>
		<name>thrips</name>
		<pose>Unspecified</pose>
		<truncated>0</truncated>
		<difficult>0</difficult>
		<bndbox>
			<xmin>376</xmin>
			<ymin>340</ymin>
			<xmax>431</xmax>
			<ymax>394</ymax>
		</bndbox>
	</object>
</annotation>
